commit_gen_cli-1.1.7-py3.11-nspkg.pth
commit_gen/cli.py
commit_gen/config.py
commit_gen/core.py
commit_gen/git_utils.py
commit_gen/providers.py
commit_gen/uninstall.py
commit_gen/prompts/changelog_prompt.txt
commit_gen/prompts/conventional.txt
commit_gen/prompts/custom.txt
commit_gen/prompts/gitmoji.txt
commit_gen_cli-1.1.7.dist-info/licenses/LICENSE
commit_gen_cli-1.1.7.dist-info/METADATA
commit_gen_cli-1.1.7.dist-info/WHEEL
commit_gen_cli-1.1.7.dist-info/entry_points.txt
commit_gen_cli-1.1.7.dist-info/namespace_packages.txt
commit_gen_cli-1.1.7.dist-info/top_level.txt
commit_gen_cli-1.1.7.dist-info/RECORD
